{
  "01-01": [
    "Vasilis"
  ],
  "01-06": [
    "Fotine",
    "Fotini",
    "Fotis",
    "Theofania",
    "Theofanis"
  ],
  "01-07": [
    "Ioanna",
    "Ioannis",
    "Prodromos",
    "Yanna",
    "Yannis"
  ],
  "01-08": [
    "Theofilos"
  ],
  "01-11": [
    "Theodosios",
    "Theodosis"
  ],
  "01-12": [
    "Tatiane",
    "Tatiani"
  ],
  "01-17": [
    "Antonia",
    "Antonios",
    "Antonis"
  ],
  "01-18": [
    "Athanasios",
    "Kyrillos",
    "Thanasis"
  ],
  "01-19": [
    "Makarios"
  ],
  "01-20": [
    "Evthymios",
    "Thymios"
  ],
  "01-21": [
    "Agne",
    "Agni",
    "Maximos",
    "Neofytos"
  ],
  "01-22": [
    "Timotheos"
  ],
  "01-23": [
    "Agathangelos"
  ],
  "01-24": [
    "Polyxene",
    "Polyxeni",
    "Xene",
    "Xeni",
    "Zosimas"
  ],
  "01-25": [
    "Gregorios",
    "Gregoris",
    "Grigorios",
    "Grigoris",
    "Margarita"
  ],
  "01-26": [
    "Xenofon"
  ],
  "01-27": [
    "Chrysostomos"
  ],
  "01-28": [
    "Palladios"
  ],
  "01-31": [
    "Evdoxia"
  ],
  "02-01": [
    "Tryfonas"
  ],
  "02-02": [
    "Ypapante",
    "Ypapanti"
  ],
  "02-04": [
    "Isidoros"
  ],
  "02-05": [
    "Agathe",
    "Agathi"
  ],
  "02-06": [
    "Fotis"
  ],
  "02-07": [
    "Parthenios",
    "Parthenis"
  ],
  "02-08": [
    "Zacharias"
  ],
  "02-10": [
    "Chara",
    "Charalambos",
    "Chariklia"
  ],
  "02-11": [
    "Vlassis"
  ],
  "02-12": [
    "Meletios",
    "Meletis"
  ],
  "02-14": [
    "Valentina",
    "Valentine",
    "Valentini",
    "Valentinos"
  ],
  "02-15": [
    "Evsevios"
  ],
  "02-19": [
    "Filothei"
  ],
  "02-23": [
    "Polykarpos"
  ],
  "02-26": [
    "Fotine",
    "Fotini",
    "Porfyrios"
  ],
  "02-27": [
    "Asklepios",
    "Asklipios"
  ],
  "03-01": [
    "Evdokia"
  ],
  "03-02": [
    "Evthalia"
  ],
  "03-07": [
    "Theodoros"
  ],
  "03-12": [
    "Theofania",
    "Theofanis"
  ],
  "03-16": [
    "Christodoulos"
  ],
  "03-17": [
    "Alekos",
    "Alexios",
    "Alexis"
  ],
  "03-19": [
    "Chrysanthos"
  ],
  "03-21": [
    "Iakovos"
  ],
  "03-25": [
    "Evangelos",
    "Vangelis"
  ],
  "04-06": [
    "Evtychios"
  ],
  "04-09": [
    "Iosif",
    "Sifis"
  ],
  "04-10": [
    "Herakles"
  ],
  "04-11": [
    "Lazaros"
  ],
  "04-12": [
    "Anthe",
    "Anthi",
    "Vaia",
    "Vaios"
  ],
  "04-15": [
    "Leonidas"
  ],
  "04-19": [
    "Anastasios",
    "Lambros",
    "Paschalis"
  ],
  "04-22": [
    "Nathanael"
  ],
  "04-23": [
    "Georgios",
    "Giorgos",
    "Yorgos"
  ],
  "04-24": [
    "Elisavet",
    "Pege",
    "Pigi",
    "Zoe",
    "Zoi"
  ],
  "04-25": [
    "Markela",
    "Markos",
    "Nike",
    "Niki"
  ],
  "04-26": [
    "Thomas"
  ],
  "04-29": [
    "Iason"
  ],
  "05-04": [
    "Pelagia"
  ],
  "05-05": [
    "Eirene",
    "Eirini",
    "Irene",
    "Irini"
  ],
  "05-06": [
    "Serafeim"
  ],
  "05-08": [
    "Arsenios",
    "Theologos"
  ],
  "05-09": [
    "Christoforos",
    "Isaias"
  ],
  "05-10": [
    "Simonas"
  ],
  "05-11": [
    "Methodios"
  ],
  "05-13": [
    "Glykeria",
    "Sergios"
  ],
  "05-14": [
    "Isidoros"
  ],
  "05-15": [
    "Achilleas"
  ],
  "05-17": [
    "Andronikos",
    "Iounia"
  ],
  "05-18": [
    "Ioulia"
  ],
  "05-20": [
    "Lydia"
  ],
  "05-21": [
    "Elena",
    "Elene",
    "Eleni",
    "Konstantina",
    "Konstantinos",
    "Lena"
  ],
  "05-29": [
    "Theodosia"
  ],
  "06-02": [
    "Nikiforos"
  ],
  "06-04": [
    "Martha"
  ],
  "06-05": [
    "Apollon",
    "Dorotheos"
  ],
  "06-08": [
    "Kalliope",
    "Kalliopi"
  ],
  "06-11": [
    "Varnavas",
    "Vartholomaios"
  ],
  "06-16": [
    "Tychon"
  ],
  "06-19": [
    "Paisios"
  ],
  "06-25": [
    "Fevronia"
  ],
  "06-29": [
    "Pavlos",
    "Petros"
  ],
  "06-30": [
    "Apostolis",
    "Apostolos"
  ],
  "07-01": [
    "Anargyros",
    "Argyris",
    "Damianos",
    "Kosmas"
  ],
  "07-04": [
    "Loukia"
  ],
  "07-07": [
    "Kyriake",
    "Kyriaki"
  ],
  "07-08": [
    "Prokopios",
    "Theofilos"
  ],
  "07-11": [
    "Evfemia",
    "Evfimia",
    "Olga"
  ],
  "07-12": [
    "Veronike",
    "Veroniki"
  ],
  "07-14": [
    "Akylas",
    "Nikodemos",
    "Nikodimos"
  ],
  "07-15": [
    "Ioulitta",
    "Kerykos",
    "Kirykos"
  ],
  "07-17": [
    "Marina"
  ],
  "07-18": [
    "Aimilianos"
  ],
  "07-20": [
    "Elias",
    "Ilias"
  ],
  "07-22": [
    "Magdalena",
    "Magdalene",
    "Magdalini",
    "Markella"
  ],
  "07-24": [
    "Christina"
  ],
  "07-25": [
    "Anna"
  ],
  "07-26": [
    "Erse",
    "Ersi",
    "Paraskeve",
    "Paraskevi"
  ],
  "07-27": [
    "Pantelis"
  ],
  "07-29": [
    "Kallinikos"
  ],
  "07-30": [
    "Andronikos"
  ],
  "07-31": [
    "Iosif",
    "Sifis"
  ],
  "08-06": [
    "Sotiria",
    "Sotiris"
  ],
  "08-07": [
    "Astero"
  ],
  "08-08": [
    "Triantafyllos"
  ],
  "08-15": [
    "Despoina",
    "Maria",
    "Panagiotis",
    "Panayotis"
  ],
  "08-16": [
    "Diomedes",
    "Diomidis"
  ],
  "08-18": [
    "Flora",
    "Floros"
  ],
  "08-20": [
    "Samouel"
  ],
  "08-25": [
    "Titos"
  ],
  "08-26": [
    "Adrianos",
    "Natalia"
  ],
  "08-27": [
    "Fanourios"
  ],
  "08-30": [
    "Alexandra",
    "Alexandros"
  ],
  "09-01": [
    "Antigone",
    "Antigoni",
    "Athena",
    "Athina",
    "Margarita",
    "Polynike",
    "Polyniki",
    "Symeon"
  ],
  "09-03": [
    "Anthimos",
    "Phoebe",
    "Phoebi"
  ],
  "09-04": [
    "Ermione",
    "Ermioni"
  ],
  "09-05": [
    "Zacharias"
  ],
  "09-09": [
    "Ioakeim"
  ],
  "09-11": [
    "Evanthia"
  ],
  "09-13": [
    "Aristeides",
    "Aristeidis",
    "Kornelios"
  ],
  "09-14": [
    "Stavros",
    "Stavroula"
  ],
  "09-15": [
    "Nikitas"
  ],
  "09-16": [
    "Evfemia"
  ],
  "09-17": [
    "Agape",
    "Agapi",
    "Elpida",
    "Sofia",
    "Sophia"
  ],
  "09-18": [
    "Ariadne",
    "Ariadni"
  ],
  "09-20": [
    "Evstathios",
    "Stathis"
  ],
  "09-22": [
    "Fokas"
  ],
  "09-23": [
    "Xanthippe",
    "Xanthippi"
  ],
  "09-24": [
    "Thekla"
  ],
  "09-25": [
    "Evfrosyne",
    "Evfrosyni"
  ],
  "09-27": [
    "Zenon",
    "Zinon"
  ],
  "09-29": [
    "Kyriakos"
  ],
  "10-02": [
    "Kyprianos"
  ],
  "10-03": [
    "Dionysis"
  ],
  "10-04": [
    "Ierotheos"
  ],
  "10-05": [
    "Charitine",
    "Charitini"
  ],
  "10-07": [
    "Polychronios",
    "Sergios"
  ],
  "10-08": [
    "Pelagia"
  ],
  "10-09": [
    "Avraam"
  ],
  "10-10": [
    "Evlambios"
  ],
  "10-15": [
    "Loukianos"
  ],
  "10-18": [
    "Loukas"
  ],
  "10-20": [
    "Artemios",
    "Gerasimos",
    "Yerasimos"
  ],
  "10-21": [
    "Sokrates",
    "Sokratis"
  ],
  "10-23": [
    "Iakovos"
  ],
  "10-26": [
    "Demetris",
    "Dimitra",
    "Dimitrios",
    "Dimitris"
  ],
  "10-27": [
    "Nestor"
  ],
  "10-30": [
    "Zenovia",
    "Zenovios",
    "Zinovia",
    "Zinovios"
  ],
  "11-01": [
    "Anargyros",
    "Argyris",
    "Damianos",
    "Kosmas"
  ],
  "11-08": [
    "Angela",
    "Angelos",
    "Gavriel",
    "Michalis",
    "Stamatis",
    "Stamos",
    "Taxiarchis"
  ],
  "11-09": [
    "Nektarios"
  ],
  "11-11": [
    "Minas",
    "Viktoras"
  ],
  "11-13": [
    "Chrysostomos"
  ],
  "11-14": [
    "Filippos"
  ],
  "11-16": [
    "Mathaios",
    "Matthaios"
  ],
  "11-18": [
    "Platonas"
  ],
  "11-21": [
    "Maria"
  ],
  "11-22": [
    "Filemon",
    "Filimon"
  ],
  "11-25": [
    "Aikaterine",
    "Aikaterini",
    "Katerina",
    "Merkourios"
  ],
  "11-26": [
    "Stelios",
    "Stergios",
    "Stylianos"
  ],
  "11-30": [
    "Andreas",
    "Andriane",
    "Andriani"
  ],
  "12-04": [
    "Varvara"
  ],
  "12-05": [
    "Diogenes",
    "Savas",
    "Savvas"
  ],
  "12-06": [
    "Nikolaos",
    "Nikoleta",
    "Nikos"
  ],
  "12-07": [
    "Amvrosios"
  ],
  "12-09": [
    "Anna"
  ],
  "12-12": [
    "Spiros",
    "Spyridon",
    "Spyros"
  ],
  "12-13": [
    "Evstratios",
    "Loukia",
    "Stratos"
  ],
  "12-15": [
    "Elevtherios",
    "Lefteris"
  ],
  "12-17": [
    "Daniel",
    "Dionysis"
  ],
  "12-20": [
    "Ignatios"
  ],
  "12-21": [
    "Themistokles",
    "Themistoklis"
  ],
  "12-22": [
    "Anastasia"
  ],
  "12-24": [
    "Evgenia"
  ],
  "12-25": [
    "Christina",
    "Christos",
    "Chrysa"
  ],
  "12-26": [
    "Emmanouil",
    "Manolis"
  ],
  "12-27": [
    "Stefanos",
    "Stephanos"
  ]
}